examples/paper_reporter.py
synago/__init__.py
synago/agent.py
synago/chat.py
synago/task.py
synago/tools/__init__.py
synago/tools/duckduckgo.py
synago/tools/web_crawl.py
synago/utils/__init__.py
synago/utils/llm.py
synago/utils/log.py
synago/utils/misc.py
tests/conftest.py
tests/test_agent.py
tests/test_tools.py
synago-0.1.0.dist-info/METADATA
synago-0.1.0.dist-info/WHEEL
synago-0.1.0.dist-info/top_level.txt
synago-0.1.0.dist-info/RECORD
